{
  "title": "vishnu-puran (1)",
  "discovered_at": "2026-07-13T17:12:31.761980+00:00",
  "edition_count": 12,
  "editions": [
    {
      "source": "open_library",
      "title": "The Vishnu Purana",
      "authors": [
        "H. H. Wilson",
        "Fitzedward Hall"
      ],
      "year": 1840,
      "languages": [
        "san",
        "eng"
      ],
      "ebook_access": "public",
      "public_domain": true,
      "ia_identifiers": [
        "vishnupurnsyst01wils",
        "vishnupuranasyst0000unse",
        "vishnupurana0000hhwi"
      ],
      "edition_count": 32,
      "isbn": [
        "9781021244307",
        "9781021444431",
        "102144443X",
        "0353306525",
        "1013941918",
        "9780343460396",
        "0343032333",
        "9780353068445",
        "9781406715415",
        "0342721755",
        "9781179685632",
        "9780824039080",
        "0353068446",
        "0342721747",
        "101547036X",
        "1846646642",
        "9781514219027",
        "9781013941917",
        "9781443739931",
        "9780343032333",
        "1015320767",
        "9781021233882",
        "9781015464018",
        "9781015470361",
        "9781846646645",
        "9781015656048",
        "1406715417",
        "9780342721740",
        "0343032325",
        "9781443722636",
        "1021244309",
        "0343460386",
        "9780343032326",
        "9781015742383",
        "9780343460389",
        "0824039084",
        "9780342721757",
        "1015656048",
        "1443722634",
        "1514219026",
        "1015464017",
        "1179685636",
        "1443739936",
        "0343460394",
        "1021233889",
        "1015742386",
        "9781015320765",
        "9780353306523"
      ],
      "publisher": [
        "Obscure Press",
        "CreateSpace Independent Publishing Platform",
        "Tr\u00fcbner",
        "Punthi Pustak",
        "Read Books",
        "Garland Pub.",
        "Hesperides Press",
        "Franklin Classics",
        "J. Murray",
        "Creative Media Partners, LLC",
        "Dissertations-G",
        "Tr\u00fcbner & co.",
        "Franklin Classics Trade Press",
        "Nabu Press"
      ],
      "ol_key": "/works/OL8720693W"
    },
    {
      "source": "archive_org",
      "identifier": "vishnu-puran-ed-1",
      "title": "Vishnu Purana",
      "creator": "Manmatha Nath Dutt",
      "year": 2025,
      "language": "eng",
      "formats": [
        "Archive BitTorrent",
        "DjVuTXT",
        "Djvu XML",
        "EPUB",
        "Item Tile",
        "Metadata",
        "OCR Page Index",
        "OCR Search Text",
        "Page Numbers JSON",
        "Scandata",
        "Single Page Processed JP2 ZIP",
        "Text PDF",
        "chOCR",
        "hOCR"
      ]
    },
    {
      "source": "archive_org",
      "identifier": "the-fundamental-message-of-islam",
      "title": "The Fundamental Message Of Islam",
      "creator": "fmoislam@protonmail.com",
      "year": null,
      "language": "eng",
      "formats": [
        "Archive BitTorrent",
        "DjVuTXT",
        "Djvu XML",
        "EPUB",
        "Item Tile",
        "Metadata",
        "OCR Page Index",
        "OCR Search Text",
        "Page Numbers JSON",
        "Scandata",
        "Single Page Processed JP2 ZIP",
        "Text PDF",
        "chOCR",
        "hOCR"
      ]
    },
    {
      "source": "archive_org",
      "identifier": "antya-karma-paddhati-pdf",
      "title": "Antya Karma Paddhati in nepali",
      "creator": "",
      "year": null,
      "language": [
        "nep",
        "Sanskrit"
      ],
      "formats": [
        "Additional Text PDF",
        "Archive BitTorrent",
        "DjVuTXT",
        "Djvu XML",
        "EPUB",
        "Image Container PDF",
        "Item Tile",
        "Metadata",
        "OCR Page Index",
        "OCR Search Text",
        "Page Numbers JSON",
        "Scandata",
        "Single Page Processed JP2 ZIP",
        "chOCR",
        "hOCR"
      ]
    },
    {
      "source": "openalex",
      "id": "https://openalex.org/W4396639696",
      "title": "Ashwamedha Yagya in Puran",
      "year": 2024,
      "is_oa": true,
      "oa_url": "https://dsiij.dsvv.ac.in/index.php/dsiij/article/download/341/246",
      "authors": [
        "Manisha Bhardwaj"
      ]
    },
    {
      "source": "openalex",
      "id": "https://openalex.org/W4205935829",
      "title": "Philosophy of some hymns of vedas and purans in relation to environmental status",
      "year": 2019,
      "is_oa": true,
      "oa_url": "https://www.allstudyjournal.com/article/648/3-4-25-224.pdf",
      "authors": [
        "Sudhir Kumar Rawat",
        "Anjana Vashishtha"
      ]
    },
    {
      "source": "open_library",
      "title": "The Vishnu Purana",
      "authors": [
        "H. H. Wilson",
        "Fitzedward Hall"
      ],
      "year": 1840,
      "languages": [
        "san",
        "eng"
      ],
      "ebook_access": "public",
      "public_domain": true,
      "ia_identifiers": [
        "vishnupurnsyst01wils",
        "vishnupuranasyst0000unse",
        "vishnupurana0000hhwi"
      ],
      "edition_count": 32,
      "isbn": [
        "9781021244307",
        "9781021444431",
        "102144443X",
        "0353306525",
        "1013941918",
        "9780343460396",
        "0343032333",
        "9780353068445",
        "9781406715415",
        "0342721755",
        "9781179685632",
        "9780824039080",
        "0353068446",
        "0342721747",
        "101547036X",
        "1846646642",
        "9781514219027",
        "9781013941917",
        "9781443739931",
        "9780343032333",
        "1015320767",
        "9781021233882",
        "9781015464018",
        "9781015470361",
        "9781846646645",
        "9781015656048",
        "1406715417",
        "9780342721740",
        "0343032325",
        "9781443722636",
        "1021244309",
        "0343460386",
        "9780343032326",
        "9781015742383",
        "9780343460389",
        "0824039084",
        "9780342721757",
        "1015656048",
        "1443722634",
        "1514219026",
        "1015464017",
        "1179685636",
        "1443739936",
        "0343460394",
        "1021233889",
        "1015742386",
        "9781015320765",
        "9780353306523"
      ],
      "publisher": [
        "Obscure Press",
        "CreateSpace Independent Publishing Platform",
        "Tr\u00fcbner",
        "Punthi Pustak",
        "Read Books",
        "Garland Pub.",
        "Hesperides Press",
        "Franklin Classics",
        "J. Murray",
        "Creative Media Partners, LLC",
        "Dissertations-G",
        "Tr\u00fcbner & co.",
        "Franklin Classics Trade Press",
        "Nabu Press"
      ],
      "ol_key": "/works/OL8720693W"
    },
    {
      "source": "archive_org",
      "identifier": "vishnu-puran-ed-1",
      "title": "Vishnu Purana",
      "creator": "Manmatha Nath Dutt",
      "year": 2025,
      "language": "eng",
      "formats": [
        "Archive BitTorrent",
        "DjVuTXT",
        "Djvu XML",
        "EPUB",
        "Item Tile",
        "Metadata",
        "OCR Page Index",
        "OCR Search Text",
        "Page Numbers JSON",
        "Scandata",
        "Single Page Processed JP2 ZIP",
        "Text PDF",
        "chOCR",
        "hOCR"
      ]
    },
    {
      "source": "archive_org",
      "identifier": "the-fundamental-message-of-islam",
      "title": "The Fundamental Message Of Islam",
      "creator": "fmoislam@protonmail.com",
      "year": null,
      "language": "eng",
      "formats": [
        "Archive BitTorrent",
        "DjVuTXT",
        "Djvu XML",
        "EPUB",
        "Item Tile",
        "Metadata",
        "OCR Page Index",
        "OCR Search Text",
        "Page Numbers JSON",
        "Scandata",
        "Single Page Processed JP2 ZIP",
        "Text PDF",
        "chOCR",
        "hOCR"
      ]
    },
    {
      "source": "archive_org",
      "identifier": "aayurved-saar-darpan-nepali",
      "title": "Aayurved Saar Darpan Nepali",
      "creator": "",
      "year": null,
      "language": "nep",
      "formats": [
        "Additional Text PDF",
        "Archive BitTorrent",
        "DjVuTXT",
        "Djvu XML",
        "EPUB",
        "Image Container PDF",
        "Item Tile",
        "Metadata",
        "OCR Page Index",
        "OCR Search Text",
        "Page Numbers JSON",
        "Scandata",
        "Single Page Processed JP2 ZIP",
        "chOCR",
        "hOCR"
      ]
    },
    {
      "source": "openalex",
      "id": "https://openalex.org/W4396639696",
      "title": "Ashwamedha Yagya in Puran",
      "year": 2024,
      "is_oa": true,
      "oa_url": "https://dsiij.dsvv.ac.in/index.php/dsiij/article/download/341/246",
      "authors": [
        "Manisha Bhardwaj"
      ]
    },
    {
      "source": "openalex",
      "id": "https://openalex.org/W4205935829",
      "title": "Philosophy of some hymns of vedas and purans in relation to environmental status",
      "year": 2019,
      "is_oa": true,
      "oa_url": "https://www.allstudyjournal.com/article/648/3-4-25-224.pdf",
      "authors": [
        "Sudhir Kumar Rawat",
        "Anjana Vashishtha"
      ]
    }
  ]
}