{
  "title": "\u0938\u0941\u0902\u0926\u0930\u0915\u093e\u0902\u0921",
  "discovered_at": "2026-07-13T17:42:32.852431+00:00",
  "edition_count": 4,
  "editions": [
    {
      "source": "archive_org",
      "identifier": "sunderkand-paath",
      "title": "Ramcharitmanas PDF | \u0917\u0940\u0924\u093e \u092a\u094d\u0930\u0947\u0938 2024 \u0928\u092f\u093e \u0938\u0902\u0938\u094d\u0915\u0930\u0923",
      "creator": "",
      "year": null,
      "language": "",
      "formats": [
        "Archive BitTorrent",
        "DjVuTXT",
        "Djvu XML",
        "Item Tile",
        "Metadata",
        "OCR Page Index",
        "OCR Search Text",
        "Page Numbers JSON",
        "Scandata",
        "Single Page Processed JP2 ZIP",
        "Text PDF",
        "chOCR",
        "hOCR"
      ]
    },
    {
      "source": "archive_org",
      "identifier": "sunderkand_202007",
      "title": "\u0938\u0941\u0902\u0926\u0930\u0915\u093e\u0902\u0921 Sunderkand",
      "creator": "",
      "year": null,
      "language": "Estonian",
      "formats": [
        "Abbyy GZ",
        "Archive BitTorrent",
        "Daisy",
        "DjVuTXT",
        "Djvu XML",
        "EPUB",
        "Item Tile",
        "Metadata",
        "Page Numbers JSON",
        "Scandata",
        "Single Page Processed JP2 ZIP",
        "Text PDF"
      ]
    },
    {
      "source": "archive_org",
      "identifier": "sunderkand-gitapress-gorakhpur",
      "title": "\u0938\u0941\u0902\u0926\u0930\u0915\u093e\u0902\u0921 \u092a\u093e\u0920 \u0939\u093f\u0902\u0926\u0940 \u092e\u0947\u0902 PDF | Sunderkand PDF",
      "creator": "\u0917\u094b\u0938\u094d\u0935\u093e\u092e\u0940 \u0924\u0941\u0932\u0938\u0940\u0926\u093e\u0938",
      "year": null,
      "language": "",
      "formats": [
        "Archive BitTorrent",
        "Daisy",
        "DjVuTXT",
        "Djvu XML",
        "EPUB",
        "Item Tile",
        "Metadata",
        "OCR Page Index",
        "OCR Search Text",
        "Page Numbers JSON",
        "Scandata",
        "Single Page Processed JP2 ZIP",
        "Text PDF",
        "chOCR",
        "hOCR"
      ]
    },
    {
      "source": "openalex",
      "id": "https://openalex.org/W7150227023",
      "title": "\u092a\u0930\u091a\u0928 \u092d\u0930\u0924\u092f \u0926\u0930\u0936\u0928 \u0914\u0930 \u0906\u0927\u0928\u0915 \u0932\u0916\u0915\u0928 \u092a\u0930\u0923\u0932 \u0915 \u0938\u092e\u0928\u0935\u092f \u0936\u0930\u0930\u092e\u091a\u0930\u0924\u092e\u0928\u0938 \u092e \u0935\u0930\u0923\u0924 \u092a\u091a\u092e\u0939\u092d\u0924 \u0938\u0926\u0927\u0924 \u0915 \u0935\u0936\u0932\u0937\u0923\u0924\u092e\u0915 \u0905\u0927\u0927\u092f\u0928",
      "year": 2026,
      "is_oa": false,
      "oa_url": null,
      "authors": [
        "\u0905\u0936\u094b\u0915 \u092e\u093f\u0936\u094d\u0930\u093e",
        "\u092e\u0928\u0935\u093f\u0928\u094d\u0926\u0930 \u092a\u093e\u0939\u0935\u093e",
        "\u0938\u0941\u0932\u0947\u0916\u093e \u091a\u094c\u0930\u0938\u093f\u092f\u093e"
      ]
    }
  ]
}